py3lite/__init__.py
py3lite/connection.py
py3lite/db.py
py3lite/decorators.py
py3lite/models.py
py3lite/query.py
py3lite/signals.py
py3lite-0.1.1.dist-info/METADATA
py3lite-0.1.1.dist-info/WHEEL
py3lite-0.1.1.dist-info/top_level.txt
py3lite-0.1.1.dist-info/RECORD
