Metadata-Version: 2.1
Name: py3lite
Version: 0.1.1
Summary: Light weight sqlite3 ORM for humans
Home-page: https://github.com/abiiranathan/py3lite
Author: Dr. Abiira Nathan
Author-email: nabiira2by2@gmail.com
License: UNKNOWN
Platform: UNKNOWN
Classifier: Programming Language :: Python :: 3
Classifier: License :: OSI Approved :: MIT License
Classifier: Operating System :: OS Independent
Requires-Python: >=3.6
